{
    "DNDConfig": null,
    "__parentReadjusting__": false,
    "_height_": {
        "type": "ref",
        "value": "preferred"
    },
    "_left_": {
        "type": "string",
        "value": "143dp"
    },
    "_margin_": [
        1,
        1,
        1,
        1
    ],
    "_padding_": [
        0,
        0,
        0,
        0
    ],
    "_skin_": "sab82e99bb3642e39aae2427d90a145a",
    "_text_": "Apple Inc.",
    "_top_": {
        "type": "string",
        "value": "43dp"
    },
    "_width_": {
        "type": "string",
        "value": "100%"
    },
    "_wrapping_": 2,
    "canUpdateUI": true,
    "centerx": {
        "type": "string",
        "value": "50%"
    },
    "channel": "mobile",
    "containerweight": 100,
    "contentalignment": 5,
    "enabled": false,
    "id": "Label0e14940e9391940",
    "info": null,
    "ipad": {
        "psp": {
            "wrapping": 2
        }
    },
    "iphone": {
        "@class": "com.kony.gen.viz.model.component.property.label.IPhoneLabelProperty",
        "psp": {
            "wrapping": 2
        }
    },
    "isvisible": true,
    "kuid": "b1d5c3f9d0574ef894ab11e65b8e562d",
    "name": "kony.ui.Label",
    "parent": "flxContainerGeneralHeader",
    "pf": "frmInfoNews",
    "tooltip": "",
    "wType": "Label",
    "zindex": 1
}